vosk_autosrt/__init__.py
vosk_autosrt/libgcc_s_seh-1.dll
vosk_autosrt/libstdc++-6.dll
vosk_autosrt/libvosk.dll
vosk_autosrt/libwinpthread-1.dll
vosk_autosrt-0.1.7.dist-info/METADATA
vosk_autosrt-0.1.7.dist-info/WHEEL
vosk_autosrt-0.1.7.dist-info/entry_points.txt
vosk_autosrt-0.1.7.dist-info/top_level.txt
vosk_autosrt-0.1.7.dist-info/RECORD
