Metadata-Version: 2.1
Name: vosk-autosrt
Version: 0.1.7
Summary: a command line utility for automatic speech recognition and subtitle generation
Home-page: https://github.com/botbahlul/vosk_autosrt
Author: Bot Bahlul
Author-email: bot.bahlul@gmail.com
License: MIT License
Requires-Dist: sounddevice >=0.4.4
Requires-Dist: vosk >=0.3.44
Requires-Dist: requests >=2.3.0
Requires-Dist: httpx >=0.13.3
Requires-Dist: urllib3 <3.0,>=1.26.0
Requires-Dist: pysrt >=1.0.1
Requires-Dist: six >=1.11.0
Requires-Dist: progressbar2 >=3.34.3
